setup.py
dsnd_probability_fara/Binomialdistribution.py
dsnd_probability_fara/Gaussiandistribution.py
dsnd_probability_fara/Generaldistribution.py
dsnd_probability_fara/__init__.py
dsnd_probability_fara.egg-info/PKG-INFO
dsnd_probability_fara.egg-info/SOURCES.txt
dsnd_probability_fara.egg-info/dependency_links.txt
dsnd_probability_fara.egg-info/not-zip-safe
dsnd_probability_fara.egg-info/top_level.txt