Metadata-Version: 1.0
Name: dsnd-probability-fara
Version: 1.2
Summary: Gaussian and Binomial distributions
Home-page: UNKNOWN
Author: faranak kh
Author-email: faranak.kheirandish@gmail.com
License: UNKNOWN
Platform: UNKNOWN
